{
  "name": "Risque",
  "fields": [
    {
      "fieldName": "processus",
      "fieldType": "String"
    },
    {
      "fieldName": "dateIdentification",
      "fieldType": "LocalDate"
    },
    {
      "fieldName": "description",
      "fieldType": "String"
    },
    {
      "fieldName": "causePotentielle",
      "fieldType": "String"
    },
    {
      "fieldName": "effetPotentiel",
      "fieldType": "String"
    },
    {
      "fieldName": "type",
      "fieldType": "TypeRisque",
      "fieldValues": "MENACE,OPPORTUNITE"
    },
    {
      "fieldName": "gravite",
      "fieldType": "EnumFive",
      "fieldValues": "ONE,TWO,THREE,FOUR,FIVE"
    },
    {
      "fieldName": "probabilite",
      "fieldType": "EnumFive",
      "fieldValues": "ONE,TWO,THREE,FOUR,FIVE"
    },
    {
      "fieldName": "criticite",
      "fieldType": "Integer"
    },
    {
      "fieldName": "traitement",
      "fieldType": "Traitement",
      "fieldValues": "ACCEPTE,REFUSE,A_TRAITER,A_TRANSFERER"
    },
    {
      "fieldName": "commentaire",
      "fieldType": "String"
    },
    {
      "fieldName": "origine",
      "fieldType": "String"
    }
  ],
  "relationships": [],
  "changelogDate": "20210302224215",
  "entityTableName": "risque",
  "dto": "no",
  "pagination": "pagination",
  "service": "no",
  "jpaMetamodelFiltering": false,
  "fluentMethods": true,
  "readOnly": false,
  "embedded": false,
  "clientRootFolder": "",
  "applications": "*"
}
